{"id":84674819,"topNeighbourId":84674820,"bottomNeighbourId":84674818,"leftNeighbourId":84674307,"rightNeighbourId":84675331,"cells":[{"l":3,"c":216},{"l":3,"c":224},{"l":3,"c":224},{"l":67,"c":224},{"l":67,"c":224},{"l":67,"c":224},{"l":67,"c":224},{"l":67,"c":224},{"l":67,"c":224},{"l":67,"c":224},{"l":67,"c":224},{"l":67,"c":224},{"l":67,"c":224},{"l":3,"c":224},{"l":3,"c":64},{"l":3,"c":64},{"l":3,"c":64},{"l":67,"c":64},{"l":67,"c":64},{"l":67,"c":64},{"l":67,"c":64},{"l":67,"c":64},{"l":67,"c":64},{"l":67,"c":64},{"l":67,"c":64},{"l":67,"c":64},{"l":67,"c":64},{"l":3,"c":2},{},{"l":3},{},{"l":67},{"l":67},{"l":67},{"l":67},{"l":67},{"l":67},{"l":67},{"l":67},{"l":67},{"l":3},{"l":3},{"l":3},{"l":67},{},{"l":67},{"l":67},{"l":67},{"l":67},{"l":67},{"l":67},{"l":67},{"l":67},{"l":3},{"l":3},{},{"l":3,"c":56},{"l":3},{"l":67},{"l":67},{"l":67},{"l":67},{"l":67},{"l":67},{"l":67},{"l":67},{"l":67},{"l":3},{"l":3},{"l":67},{},{"l":67},{"l":67},{"l":67},{"l":67},{"l":67},{"l":67},{"l":67},{"l":67},{"l":67},{"l":3},{"l":3},{"l":3},{"l":3,"c":131},{"l":3,"c":56},{},{"l":67},{"l":67},{"l":67},{"l":67},{"l":67},{"l":67},{"l":67},{"l":67},{"l":3},{"l":3},{"l":3},{"l":3},{"l":67,"c":16},{"l":67},{"l":67},{"l":67},{"l":3},{"l":3},{"l":67},{"l":67},{"l":67},{"l":67},{"l":3},{"l":3},{"l":3},{},{"l":67,"c":56},{"l":67},{"l":67},{"l":67},{"l":2},{"l":3},{"l":2},{"l":67},{"l":3},{"l":67},{"l":3},{"l":3},{"l":3},{"l":3},{"l":3},{"l":67},{"l":67},{"l":2},{"l":3},{"l":3},{"l":2},{"l":67},{"l":3},{"l":67},{"l":3},{"l":3},{"l":3},{},{},{"l":67},{"l":67},{"l":67},{"l":3},{"l":3},{"l":3},{"l":67},{"l":3},{"l":67},{"l":67},{"l":3},{},{"l":3},{"l":2},{"l":67},{"l":3},{"l":3},{"l":3},{"l":3},{"l":2},{"l":67},{"l":3},{"l":67},{},{},{"l":3},{"l":3,"c":131},{"l":67,"c":56},{"l":67},{"l":2},{"l":3},{"l":3},{"l":3},{"l":3},{"l":67},{"l":3},{"l":67},{"l":3},{},{},{"l":3,"c":1},{"l":67,"c":16},{"l":2},{"l":3},{"l":3},{"l":3},{"l":2},{"l":67},{"l":67},{"l":67},{"l":67},{},{"l":2},{},{"l":3,"c":131},{"l":3,"c":56},{"l":67},{"l":3},{"l":3},{"l":3},{"l":3},{"l":67},{"l":67},{"l":67},{"l":67},{},{"l":2},{"l":2},{},{"l":3,"c":16},{"l":67},{"l":3},{"l":3},{"l":3},{"l":2},{"l":67},{"l":67},{"l":3},{"l":67},{},{"l":2},{"l":2},{},{"l":3,"c":56},{"l":67},{"l":66},{"l":3},{"l":67},{"l":66},{"l":67},{"l":67},{},{"l":67},{"l":67},{},{"l":2},{},{"l":67,"c":16},{"l":67},{"l":66},{"l":67},{"l":67},{"l":67},{"l":67},{"l":67},{"l":67},{"l":67},{"l":67},{},{},{"l":2},{"l":67,"c":56},{"l":67},{"l":67},{"l":3},{"l":2},{"l":67},{"l":67},{"l":67},{"l":67},{"l":67},{"l":67},{"l":67},{},{"l":2},{"l":67,"c":16},{"l":3},{"l":3},{"l":67},{"l":67},{"l":67},{"l":67},{"l":3},{"l":67},{"l":67},{"l":67},{"l":67},{"l":2},{"l":2},{"l":67,"c":32},{"l":3},{"l":3},{"l":3},{"l":67},{"l":67},{"l":67},{"l":2},{"l":2},{"l":67},{"l":67},{"l":67},{"l":67},{"l":66},{"l":67},{"l":3},{"l":3},{"l":67},{"l":67},{"l":67},{"l":2},{"l":3},{"l":2},{"l":67},{"l":67},{"l":67},{"l":67},{},{"l":3,"c":8},{"l":3},{"l":3},{"l":67},{"l":67},{"l":67},{"l":3},{"l":3},{"l":3},{"l":2},{"l":67},{"l":67},{"l":67},{"l":67},{"l":3,"c":16},{"l":3},{"l":3},{"l":67},{"l":67},{"l":2},{"l":3},{"l":3},{"l":3},{"l":66},{"l":67},{"l":67},{"l":67},{"l":67,"c":128},{"l":3,"c":56},{"l":3},{"l":3},{"l":3},{"l":67},{"l":67},{"l":3},{"l":3},{"l":3},{"l":3},{"l":3},{"l":67},{"l":67},{"l":67},{"l":3,"c":16},{"l":3},{"l":3},{"l":67},{"l":67},{"l":67},{"l":67},{"l":3},{"l":3},{"l":2},{"l":67},{"l":67},{"l":67},{"l":67,"c":2},{"l":3,"c":56},{"l":3},{"l":3},{"l":3},{"l":67},{"l":67},{"l":67},{"l":67},{"l":67},{"l":66},{"l":67},{"l":67},{"l":67},{"l":67,"c":1},{"l":2},{"l":3},{},{"l":3},{"l":3},{"l":67},{"l":67},{"l":67},{"l":67},{"l":67},{"l":67},{"l":67},{"l":3},{"l":67,"c":131},{"l":2},{"l":2},{},{},{"l":3},{"l":67},{"l":67},{"l":67},{"l":2},{"l":67},{"l":67},{"l":67},{"l":67},{"l":3,"c":1},{"l":2},{},{},{},{"l":3},{"l":67},{"l":67},{"l":67},{"l":67},{"l":67},{"l":67},{"l":67},{},{"l":3,"c":131},{"l":2},{},{},{},{},{"l":2},{"l":67},{"l":67},{"l":67},{"l":67},{"l":67},{"l":67},{"l":3},{"l":2},{"l":2},{},{},{},{"l":67},{"l":67},{"l":67},{"l":67},{"l":67},{"l":67},{"l":67},{"l":2},{"l":3},{"l":3,"c":131},{"l":2},{},{},{},{"l":67},{"l":67},{"l":67},{"l":67},{"l":67},{"l":67},{"l":67},{"l":67},{"l":3},{"l":3,"c":1},{"l":2},{"l":2},{"l":3},{"l":67},{"l":67},{"l":67},{"l":67},{"l":67},{"l":67},{"l":67},{"l":67},{"l":67},{"l":67},{"l":3,"c":131},{},{"l":3},{"l":3},{"l":67},{"l":67},{"l":67},{"l":67},{"l":67},{"l":67},{"l":67},{"l":67},{"l":67},{"l":67},{"l":3,"c":1},{},{"l":3},{"l":67},{"l":67},{"l":67},{"l":67},{"l":67},{"l":67},{"l":67},{"l":67},{"l":67},{"l":67},{"l":67},{"l":67,"c":130},{"l":67,"c":56},{"l":3},{"l":67},{"l":67},{"l":67},{"l":67},{"l":67},{"l":67},{"l":67},{"l":67},{"l":67},{"l":67},{"l":67},{"l":67,"c":1},{"l":3},{"l":67},{"l":67},{"l":67},{"l":67},{"l":67},{"l":67},{"l":67},{"l":67},{"l":67},{"l":67},{"l":67},{"l":67},{"l":67,"c":131},{},{"l":67,"c":4},{"l":67,"c":4},{"l":67,"c":4},{"l":67,"c":4},{"l":67,"c":4},{"l":67,"c":4},{"l":67,"c":4},{"l":67,"c":4},{"l":67,"c":4},{"l":67,"c":4},{"l":67,"c":4},{"l":67,"c":4},{"l":67,"c":1},{"l":67,"c":14},{"l":67,"c":14},{"l":67,"c":14},{"l":67,"c":14},{"l":67,"c":14},{"l":67,"c":14},{"l":67,"c":14},{"l":67,"c":14},{"l":67,"c":14},{"l":67,"c":14},{"l":67,"c":14},{"l":67,"c":14},{"l":67,"c":8},{"l":67,"c":129}],"midgroundLayer":{"0":[],"13":[{"g":14370,"x":1127,"y":-222,"hue":[8,6,-1],"cw":144,"ch":245}],"24":[{"g":17051,"x":848,"y":-0.5,"hue":[8,6,-1],"cw":82,"ch":42}],"28":[{"g":14351,"x":-97,"y":-203,"hue":[15,11,-3],"cw":168,"ch":268}],"30":[{"g":14352,"x":73,"y":-220,"hue":[17,12,-4],"cw":189,"ch":287}],"43":[{"g":38,"x":90,"y":31.5,"hue":[17,12,-4],"cw":75,"ch":49}],"44":[{"g":700877,"x":246,"y":34.5,"hue":[47,42,26],"sx":-1,"cw":82,"ch":46},{"g":19977,"x":171,"y":-146.5,"hue":[17,12,-4],"cw":106,"ch":231}],"55":[{"g":14351,"x":1064,"y":-181.5,"hue":[6,5,-1],"cw":168,"ch":268}],"58":[{"g":700877,"x":139,"y":56,"hue":[47,42,28],"cw":82,"ch":46},{"g":30161,"x":63,"y":-9,"hue":[17,12,-2],"cw":197,"ch":103}],"70":[{"g":14369,"x":-41,"y":-125.5,"hue":[17,13,-3],"cw":186,"ch":254}],"72":[{"g":30161,"x":106,"y":12.5,"hue":[17,13,-3],"cw":197,"ch":103}],"85":[{"g":14354,"x":36,"y":-50,"hue":[18,13,-4],"cw":115,"ch":197}],"90":[{"g":17050,"x":493,"y":97,"hue":[9,7,-2],"cw":56,"ch":33}],"94":[{"g":17049,"x":824,"y":111,"hue":[10,8,-2],"cw":82,"ch":33}],"98":[{"g":17050,"x":20,"y":118.5,"hue":[19,14,-4],"cw":56,"ch":33}],"99":[{"g":700877,"x":160,"y":120.5,"hue":[49,44,26],"sx":-1,"cw":82,"ch":46},{"g":18,"x":112,"y":133.5,"hue":[19,14,-4],"cw":34,"ch":33}],"111":[{"g":14353,"x":1074,"y":-48.5,"hue":[5,3,-1],"cw":147,"ch":222}],"112":[],"113":[{"g":17049,"x":50,"y":154,"hue":[21,16,-5],"cw":82,"ch":33},{"g":30161,"x":-23,"y":77,"hue":[21,16,-5],"cw":197,"ch":103}],"116":[{"g":10120,"x":314,"y":122,"hue":[13,10,-3],"cw":80,"ch":70}],"118":[{"g":10120,"x":550,"y":121,"hue":[10,8,-2],"sx":-1,"cw":80,"ch":70}],"125":[{"g":14369,"x":1120,"y":-61,"hue":[5,4,-1],"cw":186,"ch":254}],"126":[{"g":14369,"x":-213,"y":-39.5,"hue":[22,16,-5],"cw":186,"ch":254}],"129":[{"g":10105,"x":272,"y":152.5,"hue":[15,11,-4],"cw":65,"ch":60}],"130":[{"g":33232,"x":416,"y":133.5,"hue":[13,9,-4],"sx":-1,"cw":58,"ch":69},{"look":660,"x":387,"y":193.5,"hue":[13,9,-4],"sx":-1,"id":478464}],"131":[{"g":33231,"x":424,"y":123.5,"hue":[12,8,-3],"cw":93,"ch":96},{"look":660,"x":473,"y":193.5,"hue":[12,8,-3],"id":478458}],"132":[{"g":10085,"x":589,"y":154.5,"hue":[10,7,-3],"sx":-1,"cw":64,"ch":60}],"139":[{"g":7408,"x":1110,"y":126.5,"hue":[6,5,-1],"cw":104,"ch":91},{"g":700877,"x":1278,"y":163.5,"hue":[36,35,29],"sx":-1,"cw":82,"ch":46},{"g":12040,"x":1211,"y":93.5,"hue":[6,5,-1],"cw":80,"ch":105}],"140":[{"g":14354,"x":-136,"y":36,"hue":[24,19,-6],"cw":115,"ch":197},{"g":14353,"x":-87,"y":16,"hue":[26,20,-7],"cw":147,"ch":222}],"144":[{"g":33233,"x":322,"y":173,"hue":[15,11,-4],"cw":38,"ch":45}],"145":[{"g":33231,"x":474,"y":145,"hue":[14,10,-3],"sx":-1,"cw":93,"ch":96},{"look":660,"x":430,"y":215,"hue":[14,10,-3],"sx":-1,"id":478460}],"146":[{"g":33232,"x":487,"y":155,"hue":[12,9,-3],"cw":58,"ch":69},{"look":660,"x":516,"y":215,"hue":[12,9,-3],"sx":-1,"id":478454}],"152":[{"g":14355,"x":963,"y":-12,"hue":[9,6,-2],"cw":143,"ch":247}],"153":[{"g":30161,"x":1095,"y":120,"hue":[7,5,-2],"cw":197,"ch":103}],"154":[{"g":30161,"x":-238,"y":141.5,"hue":[25,18,-6],"cw":197,"ch":103},{"g":700877,"x":74,"y":206.5,"hue":[56,50,24],"sx":-1,"cw":82,"ch":46},{"g":7399,"x":3,"y":183.5,"hue":[26,20,-6],"cw":93,"ch":70}],"157":[{"g":33241,"x":250,"y":160.5,"hue":[17,14,-4],"cw":94,"ch":87},{"look":664,"x":301,"y":236.5,"hue":[17,14,-4],"id":478467}],"158":[{"g":33231,"x":338,"y":166.5,"hue":[15,12,-4],"cw":93,"ch":96},{"look":660,"x":387,"y":236.5,"hue":[15,12,-4],"id":478463}],"159":[{"g":33231,"x":517,"y":166.5,"hue":[14,11,-3],"sx":-1,"cw":93,"ch":96},{"look":660,"x":473,"y":236.5,"hue":[14,11,-3],"sx":-1,"id":478457}],"160":[{"g":10120,"x":529,"y":186.5,"hue":[12,10,-3],"cw":80,"ch":70}],"164":[{"g":14354,"x":853,"y":57.5,"hue":[12,9,-2],"cw":115,"ch":197}],"167":[{"g":30161,"x":1052,"y":141.5,"hue":[9,7,-2],"cw":197,"ch":103}],"168":[{"g":30161,"x":-195,"y":163,"hue":[27,21,-7],"cw":197,"ch":103}],"170":[{"g":33243,"x":142,"y":209,"hue":[23,16,-5],"cw":52,"ch":62},{"g":10120,"x":142,"y":208,"hue":[23,16,-5],"cw":80,"ch":70}],"172":[{"g":33233,"x":322,"y":216,"hue":[18,13,-4],"cw":38,"ch":45}],"173":[{"g":33233,"x":408,"y":216,"hue":[17,12,-3],"cw":38,"ch":45}],"174":[{"g":700877,"x":483,"y":228,"hue":[45,41,27],"cw":82,"ch":46},{"g":33233,"x":494,"y":216,"hue":[15,11,-3],"cw":38,"ch":45}],"182":[{"g":30161,"x":-66,"y":184.5,"hue":[28,21,-6],"cw":197,"ch":103}],"183":[{"g":10124,"x":99,"y":226.5,"hue":[27,20,-6],"cw":67,"ch":72}],"184":[{"g":33241,"x":164,"y":203.5,"hue":[23,18,-6],"cw":94,"ch":87},{"look":664,"x":215,"y":279.5,"hue":[23,18,-6],"id":478474}],"185":[{"g":33241,"x":340,"y":205.5,"hue":[21,16,-5],"sx":-1,"cw":94,"ch":87},{"look":664,"x":301,"y":279.5,"hue":[21,16,-5],"id":478466}],"186":[{"g":33241,"x":426,"y":205.5,"hue":[19,14,-5],"sx":-1,"cw":94,"ch":87},{"look":664,"x":387,"y":279.5,"hue":[19,14,-5],"sx":-1,"id":478462}],"187":[{"g":10120,"x":443,"y":229.5,"hue":[18,13,-4],"cw":80,"ch":70}],"195":[],"197":[{"g":700877,"x":53,"y":271,"hue":[58,51,23],"cw":82,"ch":46}],"198":[{"g":33241,"x":211,"y":227,"hue":[27,20,-7],"sx":-1,"cw":94,"ch":87},{"look":664,"x":172,"y":301,"hue":[27,20,-7],"id":478476}],"199":[{"g":33241,"x":297,"y":227,"hue":[24,18,-6],"sx":-1,"cw":94,"ch":87},{"look":664,"x":258,"y":301,"hue":[24,18,-6],"id":478471}],"200":[{"g":33241,"x":293,"y":225,"hue":[22,17,-6],"cw":94,"ch":87},{"look":664,"x":344,"y":301,"hue":[22,17,-6],"sx":-1,"id":478465}],"206":[{"g":331,"x":817,"y":237,"hue":[14,11,-3],"cw":98,"ch":84}],"209":[{"g":7401,"x":1078,"y":231,"hue":[16,12,-4],"cw":86,"ch":94}],"211":[{"g":33242,"x":150,"y":281.5,"hue":[29,21,-7],"sx":-1,"cw":55,"ch":55}],"212":[{"g":33243,"x":185,"y":273.5,"hue":[27,20,-7],"cw":52,"ch":62},{"look":660,"x":215,"y":322.5,"hue":[27,20,-7],"sx":-1,"id":478473}],"213":[{"g":22157,"x":383,"y":320.5,"hue":[28,-3,-31],"sx":-1,"cw":116,"ch":64},{"g":33232,"x":272,"y":262.5,"hue":[25,18,-6],"cw":58,"ch":69}],"214":[{"g":33241,"x":426,"y":248.5,"hue":[23,16,-6],"sx":-1,"cw":94,"ch":87},{"look":664,"x":387,"y":322.5,"hue":[23,16,-6],"id":478461}],"215":[{"g":10120,"x":443,"y":272.5,"hue":[20,14,-5],"cw":80,"ch":70}],"218":[{"g":17052,"x":686,"y":297.5,"hue":[16,11,-3],"cw":94,"ch":54}],"219":[{"g":33232,"x":788,"y":262.5,"hue":[16,11,-3],"cw":58,"ch":69}],"221":[{"g":33225,"x":817,"y":39.5,"hue":[16,11,-3],"cw":327,"ch":342}],"223":[{"g":7400,"x":1128,"y":283.5,"hue":[18,13,-4],"cw":71,"ch":57}],"226":[{"g":10120,"x":206,"y":293,"hue":[28,21,-7],"sx":-1,"cw":80,"ch":70}],"227":[{"g":33241,"x":207,"y":268,"hue":[27,20,-6],"cw":94,"ch":87},{"look":664,"x":258,"y":344,"hue":[27,20,-6],"sx":-1,"id":478470}],"228":[{"g":33242,"x":365,"y":303,"hue":[25,19,-6],"sx":-1,"cw":55,"ch":55}],"229":[{"g":10105,"x":401,"y":303,"hue":[22,17,-5],"cw":65,"ch":60}],"230":[{"g":700877,"x":547,"y":314,"hue":[48,44,26],"sx":-1,"cw":82,"ch":46}],"232":[{"g":14355,"x":619,"y":117,"hue":[16,12,-3],"cw":143,"ch":247}],"237":[{"g":14351,"x":1021,"y":98,"hue":[19,14,-4],"cw":168,"ch":268}],"238":[{"g":30161,"x":-238,"y":270.5,"hue":[28,21,-7],"cw":197,"ch":103},{"g":12040,"x":7,"y":265.5,"hue":[28,21,-6],"cw":80,"ch":105}],"239":[{"g":700399,"x":85,"y":331.5,"hue":[29,21,-7],"cw":90,"ch":50}],"240":[{"g":10105,"x":248,"y":323.5,"hue":[28,22,-7],"sx":-1,"cw":65,"ch":60}],"242":[{"g":33242,"x":408,"y":324.5,"hue":[24,18,-6],"sx":-1,"cw":55,"ch":55}],"245":[{"g":700822,"x":622,"y":327.5,"hue":[47,43,26],"cw":74,"ch":45}],"246":[{"g":700877,"x":762,"y":335.5,"hue":[47,43,27],"sx":-1,"cw":82,"ch":46}],"250":[{"g":14370,"x":998,"y":143.5,"hue":[19,14,-4],"cw":144,"ch":245}],"251":[{"g":30161,"x":1052,"y":270.5,"hue":[21,17,-5],"cw":197,"ch":103}],"255":[{"g":33242,"x":279,"y":346,"hue":[29,21,-7],"sx":-1,"cw":55,"ch":55}],"256":[{"g":10120,"x":314,"y":337,"hue":[27,20,-7],"cw":80,"ch":70}],"263":[{"g":30161,"x":837,"y":292,"hue":[18,13,-5],"cw":197,"ch":103}],"264":[{"g":700877,"x":1063,"y":357,"hue":[49,44,26],"sx":-1,"cw":82,"ch":46},{"g":19527,"x":1011,"y":354,"hue":[19,14,-4],"cw":73,"ch":52},{"g":30161,"x":923,"y":292,"hue":[19,14,-4],"cw":197,"ch":103}],"265":[{"g":30161,"x":1009,"y":292,"hue":[21,15,-5],"cw":197,"ch":103}],"269":[{"g":17051,"x":246,"y":386.5,"hue":[28,21,-7],"cw":82,"ch":42}],"270":[{"g":700877,"x":418,"y":378.5,"hue":[56,49,23],"sx":-1,"cw":82,"ch":46}],"274":[{"g":30161,"x":622,"y":313.5,"hue":[19,14,-4],"cw":197,"ch":103}],"278":[{"g":33207,"x":1040,"y":352.5,"hue":[21,15,-5],"cw":105,"ch":77},{"g":30161,"x":966,"y":313.5,"hue":[21,15,-5],"cw":197,"ch":103}],"279":[{"g":17051,"x":1106,"y":386.5,"hue":[23,18,-6],"cw":82,"ch":42},{"g":12040,"x":1125,"y":308.5,"hue":[23,18,-6],"cw":80,"ch":105},{"g":14355,"x":1178,"y":181.5,"hue":[24,19,-6],"cw":143,"ch":247}],"287":[{"g":10120,"x":572,"y":380,"hue":[20,15,-5],"cw":80,"ch":70}],"288":[{"g":10120,"x":722,"y":379,"hue":[20,15,-4],"sx":-1,"cw":80,"ch":70}],"292":[{"g":700877,"x":1003,"y":404,"hue":[51,46,26],"cw":82,"ch":46}],"293":[{"g":700397,"x":1069,"y":400,"hue":[23,17,-5],"cw":101,"ch":58},{"g":33073,"x":950,"y":225,"hue":[23,17,-5],"cw":264,"ch":177}],"294":[{"g":14355,"x":-112,"y":224.5,"hue":[28,20,-7],"cw":143,"ch":247}],"300":[{"g":10085,"x":531,"y":410.5,"hue":[21,16,-6],"cw":64,"ch":60}],"301":[{"g":33241,"x":594,"y":375.5,"hue":[21,15,-6],"cw":94,"ch":87},{"look":664,"x":645,"y":451.5,"hue":[21,15,-6],"id":478440}],"302":[{"g":10085,"x":761,"y":412.5,"hue":[21,15,-5],"sx":-1,"cw":64,"ch":60}],"307":[{"g":14350,"x":1095,"y":225.5,"hue":[23,18,-6],"cw":119,"ch":247},{"g":30161,"x":1052,"y":356.5,"hue":[23,18,-6],"cw":197,"ch":103}],"308":[{"g":700877,"x":-119,"y":443,"hue":[57,51,23],"cw":82,"ch":46},{"g":7400,"x":-119,"y":434,"hue":[27,21,-7],"cw":71,"ch":57}],"314":[{"g":33243,"x":486,"y":424,"hue":[24,18,-6],"cw":52,"ch":62}],"317":[{"g":10085,"x":804,"y":434,"hue":[22,16,-6],"sx":-1,"cw":64,"ch":60}],"321":[{"g":700877,"x":1085,"y":443,"hue":[53,47,25],"cw":82,"ch":46},{"g":700877,"x":1235,"y":443,"hue":[54,47,24],"sx":-1,"cw":82,"ch":46}],"327":[{"g":10120,"x":443,"y":444.5,"hue":[24,19,-6],"cw":80,"ch":70}],"328":[{"g":33241,"x":508,"y":418.5,"hue":[22,18,-6],"cw":94,"ch":87},{"look":664,"x":559,"y":494.5,"hue":[22,18,-6],"id":478450}],"329":[{"g":33241,"x":684,"y":420.5,"hue":[22,17,-6],"sx":-1,"cw":94,"ch":87},{"look":664,"x":645,"y":494.5,"hue":[22,17,-6],"id":478439}],"330":[{"g":33241,"x":770,"y":420.5,"hue":[22,17,-5],"sx":-1,"cw":94,"ch":87},{"look":664,"x":731,"y":494.5,"hue":[22,17,-5],"sx":-1,"id":478429}],"331":[{"g":10085,"x":847,"y":455.5,"hue":[22,17,-5],"sx":-1,"cw":64,"ch":60}],"334":[{"g":19,"x":1039,"y":470.5,"hue":[23,16,-6],"cw":73,"ch":41}],"335":[{"g":11497,"x":1191,"y":361.5,"hue":[24,19,-6],"cw":109,"ch":139}],"336":[{"g":30161,"x":-195,"y":421,"hue":[27,21,-7],"cw":197,"ch":103},{"g":12040,"x":-36,"y":416,"hue":[28,21,-7],"cw":80,"ch":105},{"g":30161,"x":-109,"y":421,"hue":[28,21,-7],"cw":197,"ch":103}],"341":[{"g":700877,"x":397,"y":486,"hue":[55,48,24],"cw":82,"ch":46},{"g":7508,"x":402,"y":485,"hue":[25,18,-6],"cw":53,"ch":45}],"342":[{"g":33241,"x":555,"y":442,"hue":[24,18,-6],"sx":-1,"cw":94,"ch":87},{"look":664,"x":516,"y":516,"hue":[24,18,-6],"id":478453}],"343":[{"g":33241,"x":641,"y":442,"hue":[23,17,-6],"sx":-1,"cw":94,"ch":87},{"look":664,"x":602,"y":516,"hue":[23,17,-6],"id":478448}],"344":[{"g":33241,"x":637,"y":440,"hue":[23,17,-5],"cw":94,"ch":87},{"look":664,"x":688,"y":516,"hue":[23,17,-5],"sx":-1,"id":478436}],"346":[{"g":700398,"x":896,"y":485,"hue":[22,17,-5],"sx":-1,"cw":80,"ch":50}],"349":[{"g":18,"x":1101,"y":499,"hue":[23,17,-5],"cw":34,"ch":33},{"g":14370,"x":1127,"y":294,"hue":[24,17,-6],"cw":144,"ch":245},{"g":30161,"x":1095,"y":421,"hue":[24,17,-6],"cw":197,"ch":103},{"g":30161,"x":1181,"y":421,"hue":[25,20,-6],"cw":197,"ch":103}],"355":[{"g":33242,"x":494,"y":496.5,"hue":[23,17,-6],"sx":-1,"cw":55,"ch":55}],"356":[{"g":33243,"x":529,"y":488.5,"hue":[23,17,-7],"cw":52,"ch":62}],"357":[{"g":22157,"x":727,"y":535.5,"hue":[27,-3,-32],"sx":-1,"cw":116,"ch":64},{"g":33242,"x":666,"y":496.5,"hue":[24,18,-7],"sx":-1,"cw":55,"ch":55},{"look":660,"x":645,"y":537.5,"hue":[24,18,-7],"sx":-1,"id":478438}],"358":[{"g":33241,"x":770,"y":463.5,"hue":[24,18,-6],"sx":-1,"cw":94,"ch":87},{"look":664,"x":731,"y":537.5,"hue":[24,18,-6],"id":478428}],"359":[{"g":10120,"x":787,"y":487.5,"hue":[24,18,-6],"cw":80,"ch":70}],"360":[{"g":700399,"x":859,"y":503.5,"hue":[24,18,-6],"cw":90,"ch":50}],"363":[{"g":12040,"x":1211,"y":437.5,"hue":[24,19,-6],"cw":80,"ch":105}],"370":[{"g":17051,"x":461,"y":537,"hue":[22,17,-5],"cw":82,"ch":42}],"371":[{"g":33241,"x":551,"y":483,"hue":[23,18,-6],"cw":94,"ch":87},{"look":664,"x":602,"y":559,"hue":[23,18,-6],"sx":-1,"id":478447}],"372":[{"g":33232,"x":659,"y":499,"hue":[25,19,-6],"cw":58,"ch":69}],"373":[{"g":10124,"x":744,"y":506,"hue":[25,19,-7],"cw":67,"ch":72}],"374":[{"g":700771,"x":814,"y":519,"hue":[24,19,-6],"cw":107,"ch":57}],"386":[{"g":33242,"x":752,"y":539.5,"hue":[26,19,-6],"sx":-1,"cw":55,"ch":55}],"391":[{"g":30161,"x":1138,"y":485.5,"hue":[22,18,-5],"cw":197,"ch":103}],"395":[{"g":12040,"x":205,"y":498,"hue":[20,14,-5],"cw":80,"ch":105}],"399":[{"g":33242,"x":623,"y":561,"hue":[21,16,-6],"sx":-1,"cw":55,"ch":55}],"400":[{"g":10120,"x":658,"y":552,"hue":[25,18,-6],"cw":80,"ch":70}],"405":[{"g":11496,"x":1165,"y":501,"hue":[23,16,-6],"cw":80,"ch":106}],"406":[{"g":17051,"x":-98,"y":601.5,"hue":[21,16,-4],"cw":82,"ch":42},{"g":13112,"x":-85,"y":509.5,"hue":[21,16,-4],"cx":-32,"cw":152,"ch":176}],"408":[{"g":33198,"x":360,"y":531.5,"hue":[19,16,-4],"sx":-1,"cw":162,"ch":123}],"413":[{"g":700877,"x":612,"y":593.5,"hue":[52,47,25],"cw":82,"ch":46}],"414":[{"g":17049,"x":695,"y":605.5,"hue":[26,20,-6],"cw":82,"ch":33}],"418":[{"g":7401,"x":1035,"y":553.5,"hue":[23,16,-6],"cw":86,"ch":94}],"419":[{"g":17051,"x":1106,"y":601.5,"hue":[22,16,-6],"cw":82,"ch":42}],"421":[{"g":14369,"x":2,"y":412,"hue":[19,14,-5],"cw":186,"ch":254}],"422":[{"g":33201,"x":302,"y":524,"hue":[19,14,-4],"sx":-1,"cw":148,"ch":157}],"424":[{"g":33203,"x":292,"y":558,"hue":[18,14,-4],"cw":106,"ch":122},{"look":1950,"x":356,"y":577,"hue":[0,0,0],"dmin":1,"dmax":10,"anim":1,"astc":1}],"425":[{"g":32460,"x":400,"y":617,"hue":[19,14,-4],"cw":76,"ch":49}],"428":[{"g":17050,"x":665,"y":613,"hue":[23,17,-5],"cw":56,"ch":33}],"433":[{"g":700877,"x":1149,"y":615,"hue":[51,46,26],"sx":-1,"cw":82,"ch":46},{"g":7400,"x":1085,"y":606,"hue":[21,16,-4],"cw":71,"ch":57}],"434":[{"g":30161,"x":-66,"y":571.5,"hue":[18,13,-4],"cw":197,"ch":103}],"435":[{"g":20724,"x":291,"y":365.5,"hue":[19,13,-4],"sx":-1,"cw":239,"ch":345}],"438":[{"g":17049,"x":351,"y":648.5,"hue":[18,12,-5],"cw":82,"ch":33}],"439":[{"g":700877,"x":504,"y":636.5,"hue":[48,43,26],"sx":-1,"cw":82,"ch":46},{"g":1332,"x":483,"y":658.5,"hue":[18,13,-4],"sx":-1,"cw":28,"ch":16}],"445":[{"g":7397,"x":946,"y":645.5,"hue":[22,17,-5],"cw":86,"ch":44}],"446":[{"g":33243,"x":1108,"y":617.5,"hue":[21,15,-5],"sx":-1,"cw":52,"ch":62}],"448":[{"g":12221,"x":91,"y":632,"hue":[17,12,-3],"sx":-1,"cw":144,"ch":93}],"449":[{"g":31132,"x":52,"y":556,"hue":[17,12,-4],"cw":74,"ch":161},{"g":30161,"x":-23,"y":593,"hue":[17,12,-4],"cw":197,"ch":103}],"451":[{"g":33198,"x":193,"y":600,"hue":[17,12,-4],"cw":162,"ch":123}],"452":[{"g":38,"x":305,"y":655,"hue":[17,13,-4],"cw":75,"ch":49}],"459":[{"g":33243,"x":979,"y":639,"hue":[23,17,-6],"sx":-1,"cw":52,"ch":62}],"460":[{"g":33241,"x":981,"y":612,"hue":[21,15,-5],"cw":94,"ch":87},{"look":665,"x":1032,"y":688,"hue":[21,15,-5],"sx":-1,"id":478397}],"461":[{"g":30161,"x":1009,"y":593,"hue":[19,14,-4],"cw":197,"ch":103}],"462":[{"g":7400,"x":10,"y":670.5,"hue":[15,11,-2],"cw":71,"ch":57}],"463":[{"g":36060,"x":96,"y":666.5,"hue":[16,11,-2],"cw":68,"ch":63}],"464":[{"g":12040,"x":165,"y":628.5,"hue":[15,12,-2],"cw":80,"ch":105}],"472":[{"g":7507,"x":875,"y":663.5,"hue":[22,17,-5],"cw":58,"ch":60}],"473":[{"g":33242,"x":1041,"y":661.5,"hue":[20,16,-4],"sx":-1,"cw":55,"ch":55}],"474":[{"g":33243,"x":1045,"y":660.5,"hue":[19,14,-4],"cw":52,"ch":62}],"475":[{"look":665,"x":1161,"y":709.5,"hue":[18,14,-4],"sx":-1,"id":478395}],"476":[{"g":14352,"x":-99,"y":468,"hue":[13,9,-2],"cw":189,"ch":287}],"478":[{"g":700877,"x":203,"y":701,"hue":[43,39,28],"sx":-1,"cw":82,"ch":46}],"479":[{"g":700877,"x":289,"y":701,"hue":[43,39,27],"sx":-1,"cw":82,"ch":46},{"g":30161,"x":149,"y":636,"hue":[13,9,-3],"cw":197,"ch":103}],"489":[{"g":33241,"x":1067,"y":655,"hue":[17,13,-3],"cw":94,"ch":87},{"look":665,"x":1118,"y":731,"hue":[17,13,-3],"id":478396}],"490":[{"g":19977,"x":-1,"y":541.5,"hue":[12,9,-2],"cw":106,"ch":231}],"491":[{"g":30161,"x":20,"y":657.5,"hue":[13,9,-2],"cw":197,"ch":103}],"501":[{"g":12040,"x":953,"y":652.5,"hue":[18,14,-4],"cw":80,"ch":105}],"502":[{"g":33242,"x":1044,"y":711.5,"hue":[19,13,-4],"cw":55,"ch":55}],"503":[{"g":33242,"x":1182,"y":711.5,"hue":[18,13,-4],"sx":-1,"cw":55,"ch":55},{"g":14355,"x":1178,"y":525.5,"hue":[17,13,-3],"cw":143,"ch":247}],"505":[{"g":700877,"x":117,"y":744,"hue":[42,38,28],"sx":-1,"cw":82,"ch":46},{"g":11497,"x":35,"y":643,"hue":[12,8,-2],"cw":109,"ch":139}],"517":[{"g":700877,"x":1171,"y":744,"hue":[48,42,26],"cw":82,"ch":46}],"518":[{"g":30161,"x":-66,"y":700.5,"hue":[12,8,-1],"cw":197,"ch":103}],"519":[{"g":11492,"x":94,"y":699.5,"hue":[13,8,-1],"cw":80,"ch":100}],"529":[{"g":17051,"x":934,"y":773.5,"hue":[17,12,-3],"cw":82,"ch":42}],"531":[],"532":[{"g":14353,"x":-87,"y":618,"hue":[11,8,-2],"cw":147,"ch":222}],"544":[{"g":17050,"x":1009,"y":785,"hue":[18,13,-3],"cw":56,"ch":33}],"545":[{"g":30161,"x":1181,"y":722,"hue":[19,14,-3],"cw":197,"ch":103}],"546":[{"g":11496,"x":4,"y":737.5,"hue":[11,8,-2],"cw":80,"ch":106},{"g":30161,"x":-66,"y":743.5,"hue":[11,8,-2],"cw":197,"ch":103}],"559":[]},"atlasLayout":{"width":1083,"height":880,"graphicsPositions":{"18":{"sx":758,"sy":781,"sw":34,"sh":33},"19":{"sx":167,"sy":838,"sw":73,"sh":41},"38":{"sx":263,"sy":830,"sw":75,"sh":49},"331":{"sx":335,"sy":688,"sw":98,"sh":84},"1332":{"sx":883,"sy":234,"sw":18,"sh":10,"cw":28,"ch":16},"7397":{"sx":1,"sy":806,"sw":86,"sh":44},"7399":{"sx":462,"sy":472,"sw":93,"sh":70},"7400":{"sx":618,"sy":776,"sw":71,"sh":57},"7401":{"sx":1,"sy":710,"sw":86,"sh":94},"7408":{"sx":335,"sy":595,"sw":104,"sh":91},"7507":{"sx":1024,"sy":592,"sw":58,"sh":60},"7508":{"sx":758,"sy":831,"sw":53,"sh":45},"10085":{"sx":899,"sy":792,"sw":64,"sh":60},"10105":{"sx":691,"sy":781,"sw":65,"sh":60},"10120":{"sx":435,"sy":767,"sw":80,"sh":70},"10124":{"sx":687,"sy":546,"sw":67,"sh":72},"11492":{"sx":89,"sy":710,"sw":80,"sh":100},"11496":{"sx":536,"sy":669,"sw":80,"sh":106},"11497":{"sx":913,"sy":592,"sw":109,"sh":139},"12040":{"sx":618,"sy":669,"sw":80,"sh":105},"12221":{"sx":1,"sy":615,"sw":144,"sh":93},"13112":{"sx":759,"sy":514,"sw":152,"sh":176,"cx":32},"14350":{"sx":762,"sy":1,"sw":119,"sh":247},"14351":{"sx":1,"sy":345,"sw":168,"sh":268},"14352":{"sx":571,"sy":1,"sw":189,"sh":287},"14353":{"sx":759,"sy":290,"sw":147,"sh":222},"14354":{"sx":913,"sy":393,"sw":115,"sh":197},"14355":{"sx":171,"sy":345,"sw":143,"sh":247},"14369":{"sx":571,"sy":290,"sw":186,"sh":254},"14370":{"sx":316,"sy":348,"sw":144,"sh":245},"17049":{"sx":762,"sy":250,"sw":82,"sh":33},"17050":{"sx":846,"sy":250,"sw":56,"sh":33},"17051":{"sx":601,"sy":835,"sw":82,"sh":42},"17052":{"sx":289,"sy":774,"sw":94,"sh":54},"19527":{"sx":965,"sy":804,"sw":73,"sh":52},"19977":{"sx":883,"sy":1,"sw":106,"sh":231},"20724":{"sx":330,"sy":1,"sw":239,"sh":345},"22157":{"sx":171,"sy":720,"sw":116,"sh":64},"30161":{"sx":385,"sy":803,"sw":30,"sh":15,"cw":197,"ch":103},"31132":{"sx":991,"sy":1,"sw":74,"sh":161},"32460":{"sx":89,"sy":812,"sw":76,"sh":49},"33073":{"sx":385,"sy":774,"sw":40,"sh":27,"cw":264,"ch":177},"33198":{"sx":171,"sy":595,"sw":162,"sh":123},"33201":{"sx":908,"sy":234,"sw":148,"sh":157},"33203":{"sx":462,"sy":348,"sw":106,"sh":122},"33207":{"sx":796,"sy":692,"sw":105,"sh":77},"33223":{"sx":462,"sy":546,"sw":223,"sh":121},"33225":{"sx":1,"sy":1,"sw":327,"sh":342},"33231":{"sx":441,"sy":669,"sw":93,"sh":96},"33232":{"sx":1012,"sy":733,"sw":58,"sh":69},"33233":{"sx":289,"sy":720,"sw":38,"sh":45},"33241":{"sx":700,"sy":692,"sw":94,"sh":87},"33242":{"sx":1024,"sy":654,"sw":55,"sh":55},"33243":{"sx":700,"sy":620,"sw":52,"sh":62},"36060":{"sx":991,"sy":164,"sw":68,"sh":63},"700397":{"sx":796,"sy":771,"sw":101,"sh":58},"700398":{"sx":517,"sy":777,"sw":80,"sh":50},"700399":{"sx":171,"sy":786,"sw":90,"sh":50},"700771":{"sx":903,"sy":733,"sw":107,"sh":57},"700822":{"sx":340,"sy":830,"sw":74,"sh":45},"700877":{"sx":517,"sy":829,"sw":82,"sh":46}}}}
