{"id":94113792,"topNeighbourId":94114049,"bottomNeighbourId":94113793,"leftNeighbourId":94113280,"rightNeighbourId":94114304,"cells":[{"l":2},{"l":2},{"l":66},{"l":2},{"l":66},{"l":2},{"l":66},{"l":66},{"l":66},{"l":66},{"l":2},{"l":66},{"l":66},{"l":2},{"l":2},{"l":2},{"l":2},{"l":66},{"l":2},{"l":66},{"l":66},{"l":66},{"l":66},{"l":66},{"l":66},{"l":66},{"l":2},{"l":2},{"l":2},{"l":2},{"l":2},{"l":2},{"l":66},{"l":66},{"l":66},{"l":66},{"l":66},{"l":66},{"l":66},{"l":66},{"l":66},{"l":2},{"l":2},{"l":2},{"l":2},{"l":66},{"l":2},{"l":66},{"l":66},{"l":66},{"l":66},{"l":66},{"l":2},{"l":66},{"l":66},{"l":2},{"l":2},{"l":2},{"l":2},{"l":66},{"l":2},{"l":66},{"l":66},{"l":2},{"l":66},{"l":66},{"l":66},{"l":2},{"l":66},{"l":2},{"l":2},{"l":2},{"l":66},{"l":66},{"l":66},{"l":66},{"l":66},{"l":66},{"l":66},{"l":66},{"l":2},{"l":66},{"l":66},{"l":2},{"l":2},{"l":2},{"l":2},{"l":66},{"l":66},{"l":66},{"l":66},{"l":2},{"l":66},{"l":66},{"l":66},{"l":2},{"l":66},{"l":2},{"l":2},{"l":2},{"l":2},{"l":66},{"l":66},{"l":66},{"l":66},{"l":66},{"l":66},{"l":66},{"l":66},{"l":2},{"l":66},{"l":2},{"l":2},{"l":2},{"l":2},{"l":2},{"l":66},{"l":2},{"l":66},{"l":66},{"l":66},{"l":66},{"l":66},{"l":66},{"l":66},{"l":66},{"l":2},{"l":2},{"l":2},{"l":66},{"l":66},{"l":66},{"l":66},{"l":66},{"l":66},{"l":66},{"l":2},{"l":66},{"l":2},{"l":2},{"l":2},{"l":2},{"l":2},{"l":2},{"l":66},{"l":2},{"l":66},{"l":66},{"l":66},{"l":66},{"l":66},{"l":2},{"l":66},{"l":2},{"l":2},{"l":2},{"l":2},{"l":66},{"l":66},{"l":66},{"l":66},{"l":66},{"l":66},{"l":66},{"l":66},{"l":66},{"l":66},{"l":2},{"l":2},{"l":2},{"l":2},{"l":2},{"l":66},{"l":66},{"l":66},{"l":66},{"l":66},{"l":66},{"l":66},{"l":2},{"l":2},{"l":2},{"l":2},{"l":2},{"l":2},{"l":2},{"l":66},{"l":66},{"l":66},{"l":66},{"l":66},{"l":66},{"l":66},{"l":2},{"l":2},{"l":2},{"l":2},{"l":2},{"l":66},{"l":2},{"l":66},{"l":2},{"l":66},{"l":66},{"l":66},{"l":66},{"l":66},{"l":66},{"l":2},{"l":2},{"l":2},{"l":2},{"l":2},{"l":66},{"l":2},{"l":2},{"l":66},{"l":66},{"l":66},{"l":66},{"l":66},{"l":2},{"l":2},{"l":2},{"l":2},{"l":2},{"l":66},{"l":2},{"l":66},{"l":2},{"l":66},{"l":66},{"l":66},{"l":66},{"l":66},{"l":66},{"l":2},{"l":2},{"l":2},{"l":66},{"l":2},{"l":66},{"l":2},{"l":64},{"l":66},{"l":66},{"l":66},{"l":66},{"l":66},{"l":66},{"l":2},{"l":2},{"l":2},{"l":2},{"l":66},{"l":2},{"l":67},{"l":66},{"l":64},{"l":2},{"l":66},{"l":66},{"l":66},{"l":66},{"l":2},{"l":2},{"l":2},{"l":66},{"l":66},{"l":83},{"l":67},{"l":2},{"l":66},{"l":2},{"l":66},{"l":66},{"l":66},{"l":66},{"l":2},{"l":2},{"l":2},{"l":2},{"l":66},{"l":66},{"l":67},{"l":67},{"l":67},{"l":2},{"l":66},{"l":66},{"l":66},{"l":66},{"l":2},{"l":2},{"l":2},{"l":2},{"l":67},{"l":67},{"l":67},{"l":83},{"l":67},{"l":67},{"l":66},{"l":66},{"l":66},{"l":66},{"l":2},{"l":2},{"l":2},{"l":2},{"l":67},{"l":3},{"l":83},{"l":67},{"l":67},{"l":83},{"l":67},{"l":66},{"l":66},{"l":66},{"l":2},{"l":2},{"l":2},{"l":19},{"l":83},{"l":67},{"l":3},{"l":67},{"l":3},{"l":67},{"l":67},{"l":66},{"l":66},{"l":66},{"l":2},{"l":2},{"l":2},{"l":3},{"l":67},{"l":2},{"l":67},{"l":3},{"l":67},{"l":3},{"l":67},{"l":67},{"l":66},{"l":66},{"l":66},{"l":2},{"l":2},{"l":3},{"l":67},{"l":67},{"l":2},{"l":83},{"l":3},{"l":66},{"l":67},{"l":66},{"l":2},{"l":66},{"l":2},{"l":2},{"l":2},{"l":2},{"l":19},{"l":67},{"l":67},{"l":67},{},{"l":2},{"l":2},{"l":75},{"f":30,"l":66},{"l":2},{"l":2},{"l":2},{"l":2},{"l":2},{"l":67},{"l":67},{"l":83},{"l":64},{},{"l":2},{"l":2},{"l":75},{"l":2},{"l":2},{"l":2},{"l":2},{"l":2},{"l":2},{"l":2},{"l":67},{"l":67},{"l":66},{"l":64},{"l":66},{"l":2},{"l":75},{"l":66},{"l":2},{"l":2},{"l":2},{"l":2},{"l":2},{"l":2},{"l":83},{"l":67},{"l":66},{"l":2},{"l":66},{"l":75},{"l":66},{"l":66},{"l":2},{"l":2},{"l":2},{"l":2},{"l":2},{"l":2},{"l":2},{"l":67},{"l":67},{"l":67},{"l":2},{"l":11},{"l":66},{"l":66},{"l":2},{"l":2},{"l":2},{"l":2},{"l":2},{"l":2},{"l":2},{"l":67},{"l":67},{"l":75},{"l":75},{"l":2},{"l":66},{"l":2},{"l":2},{"l":2},{"l":2},{"l":2},{"l":2},{"l":2},{"l":2},{"l":2},{"l":3},{"l":67},{"l":75},{"l":2},{"l":66},{"l":2},{"l":2},{"l":2},{"l":2},{"l":2},{"l":2},{"l":2},{"l":2},{"l":2},{"l":3},{"l":2},{"l":75},{"l":66},{"l":2},{"l":2},{"l":2},{"l":2},{"l":2},{"l":2},{"l":2},{"l":2},{"l":2},{"l":2},{"l":2},{"l":2},{"l":2},{"l":11},{"l":2},{"l":2},{"l":2},{"l":2},{"l":2},{"l":2},{"l":2},{"l":2},{"l":2},{"l":2},{"l":2},{"l":2},{"l":2},{"l":2},{"l":2},{"l":2},{"l":2},{"l":2},{"l":2},{"l":2},{"l":2},{"l":2},{"l":2},{"l":2},{"l":2},{"l":2},{"l":2},{"l":2},{"l":2},{"l":2},{"l":2},{"l":2},{"l":2},{"l":2},{"l":2},{"l":2},{"l":2},{"l":2},{"l":2},{"l":2},{"l":2},{"l":2},{"l":2},{"l":2},{"l":2},{"l":2},{"l":2},{"l":2},{"l":2},{"l":2},{"l":2},{"l":2},{"l":2},{"l":2},{"l":2},{"l":2},{"l":2},{"l":2},{"l":2},{"l":2},{"l":2},{"l":2},{"l":2},{"l":2},{"l":2},{"l":2},{"l":2},{"l":2},{"l":2},{"l":2},{"l":2},{"l":2},{"l":2},{"l":2},{"l":2}],"midgroundLayer":{"285":[{"g":7993,"x":339,"y":333,"hue":[0,0,0],"cw":165,"ch":106}],"286":[{"g":700877,"x":547,"y":400,"hue":[27,-6,-28],"sx":-1,"cw":82,"ch":46}],"287":[{"g":33176,"x":544,"y":378,"hue":[27,-6,-28],"cw":111,"ch":71}],"295":[{"g":22304,"x":93,"y":398.5,"hue":[0,0,0],"cw":85,"ch":72}],"309":[{"g":33176,"x":28,"y":437,"hue":[27,-6,-28],"cw":111,"ch":71}],"339":[{"g":29420,"x":218,"y":473,"hue":[47,35,7],"cw":83,"ch":65}],"354":[{"g":29418,"x":348,"y":484.5,"hue":[47,35,7],"cw":91,"ch":76}],"368":[{"g":700877,"x":311,"y":529,"hue":[27,-6,-28],"cw":82,"ch":46}],"369":[{"g":700877,"x":461,"y":529,"hue":[27,-6,-28],"sx":-1,"cw":82,"ch":46}],"378":[{"g":29409,"x":-339,"y":110.5,"hue":[-128,-128,-128],"cx":-286,"cw":172,"ch":513}],"384":[{"g":32513,"x":427,"y":573.5,"hue":[0,0,0],"cw":248,"ch":104}],"388":[{"g":29420,"x":863,"y":537.5,"hue":[-20,-32,-60],"cw":83,"ch":65}],"399":[{"g":33196,"x":450,"y":483,"hue":[0,0,0],"cw":322,"ch":188}],"401":[{"look":1873,"x":800,"y":272,"hue":[0,0,0],"dmin":8,"dmax":15,"anim":1,"astc":1}],"403":[{"g":29418,"x":985,"y":549,"hue":[47,35,7],"sx":-1,"cw":91,"ch":76},{"g":33180,"x":904,"y":231,"hue":[0,0,0],"cw":160,"ch":393}],"406":[{"g":24012,"x":-343,"y":75.5,"hue":[0,0,0],"cw":437,"ch":557}],"411":[{"g":33163,"x":495,"y":597.5,"hue":[0,0,0],"sx":-1,"cw":50,"ch":40}],"421":[{"g":19229,"x":531,"y":-271,"hue":[-128,-128,-128],"sx":-1,"cy":-62,"cw":584,"ch":558}],"456":[{"g":22304,"x":654,"y":619,"hue":[0,0,0],"cw":85,"ch":72},{"g":29419,"x":730,"y":643,"hue":[47,35,7],"sx":-1,"cw":94,"ch":71}],"470":[{"g":33195,"x":923,"y":11.5,"hue":[0,0,0],"sx":-1,"cw":485,"ch":839}],"484":[{"g":33191,"x":1327,"y":370,"hue":[0,0,0],"sx":-1,"cx":-113,"cw":1088,"ch":481}]},"atlasLayout":{"width":1676,"height":1042,"graphicsPositions":{"7993":{"sx":1230,"sy":561,"sw":40,"sh":26,"cw":165,"ch":106},"19229":{"sx":1091,"sy":1,"sw":584,"sh":558,"cy":62},"22304":{"sx":985,"sy":484,"sw":85,"sh":72},"24012":{"sx":1,"sy":484,"sw":437,"sh":557},"29409":{"sx":440,"sy":484,"sw":172,"sh":513,"cx":286},"29418":{"sx":776,"sy":751,"sw":91,"sh":76},"29419":{"sx":889,"sy":484,"sw":94,"sh":71},"29420":{"sx":993,"sy":751,"sw":83,"sh":65},"32513":{"sx":869,"sy":751,"sw":122,"sh":51,"cw":248,"ch":104},"33163":{"sx":776,"sy":829,"sw":50,"sh":40},"33176":{"sx":776,"sy":484,"sw":111,"sh":71},"33180":{"sx":614,"sy":484,"sw":160,"sh":393},"33191":{"sx":1,"sy":1,"sw":1088,"sh":481,"cx":113},"33195":{"sx":1100,"sy":561,"sw":128,"sh":221,"cw":485,"ch":839},"33196":{"sx":776,"sy":561,"sw":322,"sh":188},"700877":{"sx":869,"sy":804,"sw":82,"sh":46}}},"foreground":true}
